arkitekt_gateway/__init__.py
arkitekt_gateway/main.py
arkitekt_gateway/sidecar.py
arkitekt_gateway/bin/arkitekt-sidecar
arkitekt_gateway-1.2.1.dist-info/METADATA
arkitekt_gateway-1.2.1.dist-info/WHEEL
arkitekt_gateway-1.2.1.dist-info/entry_points.txt
arkitekt_gateway-1.2.1.dist-info/RECORD
