Metadata-Version: 2.4
Name: arkitekt-gateway
Version: 1.2.1
Summary: Add your description here
Author-email: Your Name <your.email@example.com>
Keywords: arkitekt,gateway
Classifier: Development Status :: 4 - Beta
Classifier: License :: OSI Approved :: MIT License
Classifier: Operating System :: OS Independent
Classifier: Programming Language :: Python :: 3
Classifier: Programming Language :: Python :: 3.12
Requires-Python: >=3.11
Requires-Dist: aiohttp>=3.12.14
Requires-Dist: typer>=0.16.0
